ape_risk/__init__.py
ape_risk/py.typed
ape_risk/version.py
ape_risk/stats/__init__.py
ape_risk/stats/montecarlo.py
ape_risk/strategies/__init__.py
ape_risk/strategies/core.py
ape_risk/strategies/simulation.py
ape_risk-0.1.0a4.dist-info/LICENSE
ape_risk-0.1.0a4.dist-info/METADATA
ape_risk-0.1.0a4.dist-info/WHEEL
ape_risk-0.1.0a4.dist-info/top_level.txt
ape_risk-0.1.0a4.dist-info/RECORD
