Metadata-Version: 2.1
Name: ape-risk
Version: 0.1.0a4
Summary: ape-risk: DeFi risk analysis as an ApeWorX plugin
Home-page: https://github.com/smolquants/ape-risk
Author: smolquants
Author-email: dev@smolquants.xyz
License: Apache-2.0
Keywords: ethereum
Platform: UNKNOWN
Classifier: Development Status :: 5 - Production/Stable
Classifier: Intended Audience :: Developers
Classifier: License :: OSI Approved :: Apache Software License
Classifier: Natural Language :: English
Classifier: Operating System :: MacOS
Classifier: Operating System :: POSIX
Classifier: Programming Language :: Python :: 3
Classifier: Programming Language :: Python :: 3.8
Classifier: Programming Language :: Python :: 3.9
Classifier: Programming Language :: Python :: 3.10
Classifier: Programming Language :: Python :: 3.11
Requires-Python: >=3.8,<4
Requires-Dist: eth-ape <0.7.0,>=0.6.12
Requires-Dist: pandas
Requires-Dist: scipy
Requires-Dist: numpy <2.0,>=1.21
Requires-Dist: hypothesis <7.0,>=6.2.0
Provides-Extra: dev
Requires-Dist: pytest >=6.0 ; extra == 'dev'
Requires-Dist: pytest-xdist ; extra == 'dev'
Requires-Dist: pytest-cov ; extra == 'dev'
Requires-Dist: black >=22.6.0 ; extra == 'dev'
Requires-Dist: mypy >=0.971 ; extra == 'dev'
Requires-Dist: flake8 >=4.0.1 ; extra == 'dev'
Requires-Dist: isort >=5.10.1 ; extra == 'dev'
Requires-Dist: setuptools <60.0 ; extra == 'dev'
Requires-Dist: wheel ; extra == 'dev'
Requires-Dist: twine ; extra == 'dev'
Requires-Dist: commitizen ; extra == 'dev'
Requires-Dist: pre-commit ; extra == 'dev'
Requires-Dist: pytest-watch ; extra == 'dev'
Requires-Dist: IPython ; extra == 'dev'
Requires-Dist: ipdb ; extra == 'dev'
Requires-Dist: matplotlib ; extra == 'dev'
Provides-Extra: lint
Requires-Dist: black >=22.6.0 ; extra == 'lint'
Requires-Dist: mypy >=0.971 ; extra == 'lint'
Requires-Dist: flake8 >=4.0.1 ; extra == 'lint'
Requires-Dist: isort >=5.10.1 ; extra == 'lint'
Provides-Extra: release
Requires-Dist: setuptools <60.0 ; extra == 'release'
Requires-Dist: wheel ; extra == 'release'
Requires-Dist: twine ; extra == 'release'
Provides-Extra: test
Requires-Dist: pytest >=6.0 ; extra == 'test'
Requires-Dist: pytest-xdist ; extra == 'test'
Requires-Dist: pytest-cov ; extra == 'test'
